mkdocs_external_link_processor/__init__.py
mkdocs_external_link_processor/mkdocs_external_link_processor.py
mkdocs_external_link_processor-0.1.0.dist-info/LICENSE.md
mkdocs_external_link_processor-0.1.0.dist-info/METADATA
mkdocs_external_link_processor-0.1.0.dist-info/WHEEL
mkdocs_external_link_processor-0.1.0.dist-info/entry_points.txt
mkdocs_external_link_processor-0.1.0.dist-info/top_level.txt
mkdocs_external_link_processor-0.1.0.dist-info/RECORD
